{
  "count": 15,
  "fetched_at_utc": "2026-07-18T23:04:26.770319Z",
  "source": "https://aq.nbro.gov.lk/invoker.php",
  "stations": [
    {
      "co2": 477.103,
      "description": "Anuradhapura",
      "latitude": 8.33356,
      "longitude": 80.41497,
      "meta_device_id": "NEAANU00000001",
      "name": "Anuradhapura",
      "now_cast": 32.2265,
      "now_cast_timestamp": 1784410200000,
      "pm10": 18.55,
      "pm100": 43.4167,
      "pm25": 26.8985,
      "pm25_band_range": [
        25.1,
        50.0
      ],
      "sl_aqi": 54.0,
      "sl_aqi_est": 55,
      "sl_aqi_label": "Moderate",
      "sl_aqi_range": [
        51,
        100
      ],
      "temperature": 30.6955,
      "timestamp": 1784410200000,
      "timestamp_iso_utc": "2026-07-18T21:30:00Z",
      "us_aqi": 93.0
    },
    {
      "co2": 484.506,
      "description": "Badulla",
      "latitude": 6.990113,
      "longitude": 81.05676,
      "meta_device_id": "aq02",
      "name": "Badulla ",
      "now_cast": 22.1523,
      "now_cast_timestamp": 1784345400000,
      "pm10": 16.15,
      "pm100": 25.1833,
      "pm25": 22.1763,
      "pm25_band_range": [
        0.0,
        25.0
      ],
      "sl_aqi": 44.0,
      "sl_aqi_est": 44,
      "sl_aqi_label": "Good",
      "sl_aqi_range": [
        0,
        50
      ],
      "temperature": 23.07,
      "timestamp": 1784410200000,
      "timestamp_iso_utc": "2026-07-18T21:30:00Z",
      "us_aqi": 72.0
    },
    {
      "co2": 462.592,
      "description": "aqbatticaloa001",
      "latitude": 7.7124324,
      "longitude": 81.7014,
      "meta_device_id": "BATTI000001",
      "name": "Batticaloa",
      "now_cast": 22.4725,
      "now_cast_timestamp": 1784410200000,
      "pm10": 14.2667,
      "pm100": 24.6333,
      "pm25": 21.1652,
      "pm25_band_range": [
        0.0,
        25.0
      ],
      "sl_aqi": 42.0,
      "sl_aqi_est": 42,
      "sl_aqi_label": "Good",
      "sl_aqi_range": [
        0,
        50
      ],
      "temperature": 29.0948,
      "timestamp": 1784410200000,
      "timestamp_iso_utc": "2026-07-18T21:30:00Z",
      "us_aqi": 73.0
    },
    {
      "co2": 556.022,
      "description": "AQCOL000001",
      "latitude": 6.9056125,
      "longitude": 79.87293,
      "meta_device_id": "COL0000001",
      "name": "Colombo 07",
      "now_cast": 13.7643,
      "now_cast_timestamp": 1784410200000,
      "pm10": 8.85,
      "pm100": 15.3667,
      "pm25": 13.6909,
      "pm25_band_range": [
        0.0,
        25.0
      ],
      "sl_aqi": 27.0,
      "sl_aqi_est": 27,
      "sl_aqi_label": "Good",
      "sl_aqi_range": [
        0,
        50
      ],
      "temperature": 31.4993,
      "timestamp": 1784410200000,
      "timestamp_iso_utc": "2026-07-18T21:30:00Z",
      "us_aqi": 54.0
    },
    {
      "co2": -1.0,
      "description": "Dambulla air quality sensor",
      "latitude": 7.862204,
      "longitude": 80.64585,
      "meta_device_id": "Dav00002",
      "name": "Dambulla",
      "now_cast": 14.6573,
      "now_cast_timestamp": 1784410200000,
      "pm10": 10.6607,
      "pm100": 15.9286,
      "pm25": 14.0714,
      "pm25_band_range": [
        0.0,
        25.0
      ],
      "sl_aqi": 28.0,
      "sl_aqi_est": 28,
      "sl_aqi_label": "Good",
      "sl_aqi_range": [
        0,
        50
      ],
      "temperature": 31.4691,
      "timestamp": 1784410200000,
      "timestamp_iso_utc": "2026-07-18T21:30:00Z",
      "us_aqi": 56.0
    },
    {
      "co2": 486.569,
      "description": "Hambantota",
      "latitude": 6.1242557,
      "longitude": 81.12618,
      "meta_device_id": "verit03",
      "name": "Hambantota ",
      "now_cast": 26.2249,
      "now_cast_timestamp": 1784410200000,
      "pm10": 15.9833,
      "pm100": 27.9833,
      "pm25": 24.3147,
      "pm25_band_range": [
        0.0,
        25.0
      ],
      "sl_aqi": 48.0,
      "sl_aqi_est": 49,
      "sl_aqi_label": "Good",
      "sl_aqi_range": [
        0,
        50
      ],
      "temperature": 28.8748,
      "timestamp": 1784410200000,
      "timestamp_iso_utc": "2026-07-18T21:30:00Z",
      "us_aqi": 81.0
    },
    {
      "co2": 457.402,
      "description": "Jaffna",
      "latitude": 9.737238,
      "longitude": 80.019455,
      "meta_device_id": "JAFPRIVAT0001",
      "name": "Jaffna",
      "now_cast": 8.53232,
      "now_cast_timestamp": 1784410200000,
      "pm10": 6.86667,
      "pm100": 9.5,
      "pm25": 8.89452,
      "pm25_band_range": [
        0.0,
        25.0
      ],
      "sl_aqi": 17.0,
      "sl_aqi_est": 18,
      "sl_aqi_label": "Good",
      "sl_aqi_range": [
        0,
        50
      ],
      "temperature": 30.8063,
      "timestamp": 1784410200000,
      "timestamp_iso_utc": "2026-07-18T21:30:00Z",
      "us_aqi": 35.0
    },
    {
      "co2": 455.655,
      "description": "AQKegalle",
      "latitude": 7.253432,
      "longitude": 80.34929,
      "meta_device_id": "Kegalle0001",
      "name": "Kegalle",
      "now_cast": 39.3848,
      "now_cast_timestamp": 1784410200000,
      "pm10": 33.1667,
      "pm100": 52.25,
      "pm25": 43.6694,
      "pm25_band_range": [
        25.1,
        50.0
      ],
      "sl_aqi": 87.0,
      "sl_aqi_est": 88,
      "sl_aqi_label": "Moderate",
      "sl_aqi_range": [
        51,
        100
      ],
      "temperature": 29.4783,
      "timestamp": 1784410200000,
      "timestamp_iso_utc": "2026-07-18T21:30:00Z",
      "us_aqi": 110.0
    },
    {
      "co2": 425.698,
      "description": "Kohuwla",
      "latitude": 6.870283,
      "longitude": 79.8771,
      "meta_device_id": "kohu01",
      "name": "Kohuwla ",
      "now_cast": 5.14322,
      "now_cast_timestamp": 1784410200000,
      "pm10": 4.18333,
      "pm100": 6.18333,
      "pm25": 5.28713,
      "pm25_band_range": [
        0.0,
        25.0
      ],
      "sl_aqi": 10.0,
      "sl_aqi_est": 11,
      "sl_aqi_label": "Good",
      "sl_aqi_range": [
        0,
        50
      ],
      "temperature": 30.5027,
      "timestamp": 1784410200000,
      "timestamp_iso_utc": "2026-07-18T21:30:00Z",
      "us_aqi": 21.0
    },
    {
      "co2": 445.686,
      "description": "AQKolonnawa",
      "latitude": 6.932626,
      "longitude": 79.89155,
      "meta_device_id": "Colombo00003",
      "name": "Kolonnawa",
      "now_cast": 24.9355,
      "now_cast_timestamp": 1784410200000,
      "pm10": 17.9,
      "pm100": 28.2833,
      "pm25": 24.7623,
      "pm25_band_range": [
        0.0,
        25.0
      ],
      "sl_aqi": 49.0,
      "sl_aqi_est": 50,
      "sl_aqi_label": "Good",
      "sl_aqi_range": [
        0,
        50
      ],
      "temperature": 30.2598,
      "timestamp": 1784410200000,
      "timestamp_iso_utc": "2026-07-18T21:30:00Z",
      "us_aqi": 78.0
    },
    {
      "co2": 1045.01,
      "description": "Mannar",
      "latitude": 8.988006,
      "longitude": 79.907524,
      "meta_device_id": "MAN10234s",
      "name": "Mannar",
      "now_cast": 14.4794,
      "now_cast_timestamp": 1784248200000,
      "pm10": 9.0,
      "pm100": 24.0,
      "pm25": 13.4478,
      "pm25_band_range": [
        0.0,
        25.0
      ],
      "sl_aqi": 26.0,
      "sl_aqi_est": 27,
      "sl_aqi_label": "Good",
      "sl_aqi_range": [
        0,
        50
      ],
      "temperature": 25.74,
      "timestamp": 1784248200000,
      "timestamp_iso_utc": "2026-07-17T00:30:00Z",
      "us_aqi": 56.0
    },
    {
      "co2": 464.571,
      "description": null,
      "latitude": 8.028199,
      "longitude": 79.84147,
      "meta_device_id": "NEA8000006",
      "name": "Puttalam",
      "now_cast": 12.1709,
      "now_cast_timestamp": 1784410200000,
      "pm10": 8.0678,
      "pm100": 17.4576,
      "pm25": 12.1241,
      "pm25_band_range": [
        0.0,
        25.0
      ],
      "sl_aqi": 24.0,
      "sl_aqi_est": 24,
      "sl_aqi_label": "Good",
      "sl_aqi_range": [
        0,
        50
      ],
      "temperature": 30.71,
      "timestamp": 1784410200000,
      "timestamp_iso_utc": "2026-07-18T21:30:00Z",
      "us_aqi": 51.0
    },
    {
      "co2": -1.0,
      "description": "Rathanapura",
      "latitude": 6.7137103,
      "longitude": 80.38062,
      "meta_device_id": "NEA8000013",
      "name": "Rathnapura ",
      "now_cast": 13.2541,
      "now_cast_timestamp": 1784410200000,
      "pm10": 6.16667,
      "pm100": 17.1167,
      "pm25": 12.0604,
      "pm25_band_range": [
        0.0,
        25.0
      ],
      "sl_aqi": 24.0,
      "sl_aqi_est": 24,
      "sl_aqi_label": "Good",
      "sl_aqi_range": [
        0,
        50
      ],
      "temperature": 29.727,
      "timestamp": 1784410200000,
      "timestamp_iso_utc": "2026-07-18T21:30:00Z",
      "us_aqi": 53.0
    },
    {
      "co2": -1.0,
      "description": "METTRINCOMALEE",
      "latitude": 8.639678,
      "longitude": 81.2028,
      "meta_device_id": "NBROTRINCOMALEE",
      "name": "Trincomalee",
      "now_cast": 13.4181,
      "now_cast_timestamp": 1784410200000,
      "pm10": 9.36667,
      "pm100": 14.3333,
      "pm25": 12.929,
      "pm25_band_range": [
        0.0,
        25.0
      ],
      "sl_aqi": 25.0,
      "sl_aqi_est": 26,
      "sl_aqi_label": "Good",
      "sl_aqi_range": [
        0,
        50
      ],
      "temperature": 27.4728,
      "timestamp": 1784410200000,
      "timestamp_iso_utc": "2026-07-18T21:30:00Z",
      "us_aqi": 54.0
    },
    {
      "co2": -1.0,
      "description": "Vavuniya",
      "latitude": 8.761628,
      "longitude": 80.49619,
      "meta_device_id": "VAVUNIYA0021",
      "name": "Vavuniya",
      "now_cast": 13.0125,
      "now_cast_timestamp": 1784410200000,
      "pm10": 9.1,
      "pm100": 15.8333,
      "pm25": 12.8788,
      "pm25_band_range": [
        0.0,
        25.0
      ],
      "sl_aqi": 25.0,
      "sl_aqi_est": 26,
      "sl_aqi_label": "Good",
      "sl_aqi_range": [
        0,
        50
      ],
      "temperature": 34.0735,
      "timestamp": 1784410200000,
      "timestamp_iso_utc": "2026-07-18T21:30:00Z",
      "us_aqi": 53.0
    }
  ]
}
