{
  "count": 14,
  "fetched_at_utc": "2026-05-12T19:16:14.242001Z",
  "source": "https://aq.nbro.gov.lk/invoker.php",
  "stations": [
    {
      "co2": 492.178,
      "description": "Anuradhapura",
      "latitude": 8.33356,
      "longitude": 80.41497,
      "meta_device_id": "NEAANU00000001",
      "name": "Anuradhapura",
      "now_cast": 1.41585,
      "now_cast_timestamp": 1778538600000,
      "pm10": 0.5,
      "pm100": 1.8,
      "pm25": 1.23861,
      "pm25_band_range": [
        0.0,
        25.0
      ],
      "sl_aqi": 2.0,
      "sl_aqi_est": 2,
      "sl_aqi_label": "Good",
      "sl_aqi_range": [
        0,
        50
      ],
      "temperature": 30.2798,
      "timestamp": 1778603400000,
      "timestamp_iso_utc": "2026-05-12T16:30:00Z",
      "us_aqi": 6.0
    },
    {
      "co2": 504.139,
      "description": "Badulla",
      "latitude": 6.990113,
      "longitude": 81.05676,
      "meta_device_id": "aq02",
      "name": "Badulla ",
      "now_cast": 18.7248,
      "now_cast_timestamp": 1778607000000,
      "pm10": 17.3833,
      "pm100": 25.1667,
      "pm25": 22.674,
      "pm25_band_range": [
        0.0,
        25.0
      ],
      "sl_aqi": 45.0,
      "sl_aqi_est": 45,
      "sl_aqi_label": "Good",
      "sl_aqi_range": [
        0,
        50
      ],
      "temperature": 25.4965,
      "timestamp": 1778607000000,
      "timestamp_iso_utc": "2026-05-12T17:30:00Z",
      "us_aqi": 65.0
    },
    {
      "co2": 866.114,
      "description": "aqbatticaloa001",
      "latitude": 7.7124324,
      "longitude": 81.7014,
      "meta_device_id": "BATTI000001",
      "name": "Batticaloa",
      "now_cast": 0.0,
      "now_cast_timestamp": 0,
      "pm10": 3.28571,
      "pm100": 7.28571,
      "pm25": 6.45293,
      "pm25_band_range": [
        0.0,
        25.0
      ],
      "sl_aqi": 13.0,
      "sl_aqi_est": 13,
      "sl_aqi_label": "Good",
      "sl_aqi_range": [
        0,
        50
      ],
      "temperature": 25.8171,
      "timestamp": 1778491800000,
      "timestamp_iso_utc": "2026-05-11T09:30:00Z",
      "us_aqi": 0.0
    },
    {
      "co2": -1.0,
      "description": "Dambulla air quality sensor",
      "latitude": 7.862204,
      "longitude": 80.64585,
      "meta_device_id": "Dav00002",
      "name": "Dambulla",
      "now_cast": 20.2066,
      "now_cast_timestamp": 1778607000000,
      "pm10": 17.1167,
      "pm100": 24.25,
      "pm25": 22.766,
      "pm25_band_range": [
        0.0,
        25.0
      ],
      "sl_aqi": 45.0,
      "sl_aqi_est": 46,
      "sl_aqi_label": "Good",
      "sl_aqi_range": [
        0,
        50
      ],
      "temperature": 30.54,
      "timestamp": 1778607000000,
      "timestamp_iso_utc": "2026-05-12T17:30:00Z",
      "us_aqi": 68.0
    },
    {
      "co2": 590.628,
      "description": "Jaffna",
      "latitude": 9.737238,
      "longitude": 80.019455,
      "meta_device_id": "JAFPRIVAT0001",
      "name": "Jaffna",
      "now_cast": 7.14744,
      "now_cast_timestamp": 1778607000000,
      "pm10": 3.21667,
      "pm100": 6.46667,
      "pm25": 6.29396,
      "pm25_band_range": [
        0.0,
        25.0
      ],
      "sl_aqi": 12.0,
      "sl_aqi_est": 13,
      "sl_aqi_label": "Good",
      "sl_aqi_range": [
        0,
        50
      ],
      "temperature": 31.5828,
      "timestamp": 1778607000000,
      "timestamp_iso_utc": "2026-05-12T17:30:00Z",
      "us_aqi": 29.0
    },
    {
      "co2": 421.379,
      "description": "Kohuwla",
      "latitude": 6.870283,
      "longitude": 79.8771,
      "meta_device_id": "kohu01",
      "name": "Kohuwla ",
      "now_cast": 14.8862,
      "now_cast_timestamp": 1778607000000,
      "pm10": 11.3,
      "pm100": 15.0667,
      "pm25": 13.8977,
      "pm25_band_range": [
        0.0,
        25.0
      ],
      "sl_aqi": 27.0,
      "sl_aqi_est": 28,
      "sl_aqi_label": "Good",
      "sl_aqi_range": [
        0,
        50
      ],
      "temperature": 28.736,
      "timestamp": 1778607000000,
      "timestamp_iso_utc": "2026-05-12T17:30:00Z",
      "us_aqi": 57.0
    },
    {
      "co2": -1.0,
      "description": "Kurunegala 1",
      "latitude": 7.493901,
      "longitude": 80.367744,
      "meta_device_id": "NEA8000010",
      "name": "Kurunegala ",
      "now_cast": 0.0,
      "now_cast_timestamp": 0,
      "pm10": 10.0,
      "pm100": 11.75,
      "pm25": 11.0632,
      "pm25_band_range": [
        0.0,
        25.0
      ],
      "sl_aqi": 22.0,
      "sl_aqi_est": 22,
      "sl_aqi_label": "Good",
      "sl_aqi_range": [
        0,
        50
      ],
      "temperature": 26.575,
      "timestamp": 1778495400000,
      "timestamp_iso_utc": "2026-05-11T10:30:00Z",
      "us_aqi": 0.0
    },
    {
      "co2": 1384.33,
      "description": "Mannar",
      "latitude": 8.988006,
      "longitude": 79.907524,
      "meta_device_id": "MAN10234s",
      "name": "Mannar",
      "now_cast": 1.98784,
      "now_cast_timestamp": 1778517000000,
      "pm10": 9.66667,
      "pm100": 16.3167,
      "pm25": 14.0076,
      "pm25_band_range": [
        0.0,
        25.0
      ],
      "sl_aqi": 28.0,
      "sl_aqi_est": 28,
      "sl_aqi_label": "Good",
      "sl_aqi_range": [
        0,
        50
      ],
      "temperature": 31.3,
      "timestamp": 1778607000000,
      "timestamp_iso_utc": "2026-05-12T17:30:00Z",
      "us_aqi": 8.0
    },
    {
      "co2": 461.418,
      "description": "Nuwaraeliya",
      "latitude": 6.9681544,
      "longitude": 80.77159,
      "meta_device_id": "Nuwaraeliya0010",
      "name": "Nuwaraeliya",
      "now_cast": 34.272,
      "now_cast_timestamp": 1778607000000,
      "pm10": 23.6,
      "pm100": 41.0167,
      "pm25": 34.3629,
      "pm25_band_range": [
        25.1,
        50.0
      ],
      "sl_aqi": 69.0,
      "sl_aqi_est": 69,
      "sl_aqi_label": "Moderate",
      "sl_aqi_range": [
        51,
        100
      ],
      "temperature": 22.6057,
      "timestamp": 1778607000000,
      "timestamp_iso_utc": "2026-05-12T17:30:00Z",
      "us_aqi": 97.0
    },
    {
      "co2": 749.539,
      "description": "aqpolonnaruwa001",
      "latitude": 7.9132895,
      "longitude": 81.04993,
      "meta_device_id": "polonnaruwa0001",
      "name": "Polonnaruwa",
      "now_cast": 20.1551,
      "now_cast_timestamp": 1778607000000,
      "pm10": 11.2167,
      "pm100": 21.0167,
      "pm25": 18.1983,
      "pm25_band_range": [
        0.0,
        25.0
      ],
      "sl_aqi": 36.0,
      "sl_aqi_est": 36,
      "sl_aqi_label": "Good",
      "sl_aqi_range": [
        0,
        50
      ],
      "temperature": 27.4397,
      "timestamp": 1778607000000,
      "timestamp_iso_utc": "2026-05-12T17:30:00Z",
      "us_aqi": 68.0
    },
    {
      "co2": 472.668,
      "description": null,
      "latitude": 8.028199,
      "longitude": 79.84147,
      "meta_device_id": "NEA8000006",
      "name": "Puttalam",
      "now_cast": 21.8555,
      "now_cast_timestamp": 1778607000000,
      "pm10": 14.4576,
      "pm100": 94.661,
      "pm25": 20.4239,
      "pm25_band_range": [
        0.0,
        25.0
      ],
      "sl_aqi": 40.0,
      "sl_aqi_est": 41,
      "sl_aqi_label": "Good",
      "sl_aqi_range": [
        0,
        50
      ],
      "temperature": 29.9083,
      "timestamp": 1778607000000,
      "timestamp_iso_utc": "2026-05-12T17:30:00Z",
      "us_aqi": 71.0
    },
    {
      "co2": -1.0,
      "description": "Rathanapura",
      "latitude": 6.7137103,
      "longitude": 80.38062,
      "meta_device_id": "NEA8000013",
      "name": "Rathnapura ",
      "now_cast": 37.688,
      "now_cast_timestamp": 1778585400000,
      "pm10": 27.3095,
      "pm100": 46.8333,
      "pm25": 37.236,
      "pm25_band_range": [
        25.1,
        50.0
      ],
      "sl_aqi": 74.0,
      "sl_aqi_est": 75,
      "sl_aqi_label": "Moderate",
      "sl_aqi_range": [
        51,
        100
      ],
      "temperature": 29.4138,
      "timestamp": 1778585400000,
      "timestamp_iso_utc": "2026-05-12T11:30:00Z",
      "us_aqi": 106.0
    },
    {
      "co2": -1.0,
      "description": "METTRINCOMALEE",
      "latitude": 8.639678,
      "longitude": 81.2028,
      "meta_device_id": "NBROTRINCOMALEE",
      "name": "Trincomalee",
      "now_cast": 4.05497,
      "now_cast_timestamp": 1778607000000,
      "pm10": 3.6,
      "pm100": 5.15,
      "pm25": 4.61014,
      "pm25_band_range": [
        0.0,
        25.0
      ],
      "sl_aqi": 9.0,
      "sl_aqi_est": 9,
      "sl_aqi_label": "Good",
      "sl_aqi_range": [
        0,
        50
      ],
      "temperature": 26.465,
      "timestamp": 1778607000000,
      "timestamp_iso_utc": "2026-05-12T17:30:00Z",
      "us_aqi": 17.0
    },
    {
      "co2": -1.0,
      "description": "Vavuniya",
      "latitude": 8.761628,
      "longitude": 80.49619,
      "meta_device_id": "VAVUNIYA0021",
      "name": "Vavuniya",
      "now_cast": 4.78295,
      "now_cast_timestamp": 1778607000000,
      "pm10": 0.633333,
      "pm100": 1.51667,
      "pm25": 1.14322,
      "pm25_band_range": [
        0.0,
        25.0
      ],
      "sl_aqi": 2.0,
      "sl_aqi_est": 2,
      "sl_aqi_label": "Good",
      "sl_aqi_range": [
        0,
        50
      ],
      "temperature": 35.0452,
      "timestamp": 1778607000000,
      "timestamp_iso_utc": "2026-05-12T17:30:00Z",
      "us_aqi": 19.0
    }
  ]
}
