{
  "count": 13,
  "fetched_at_utc": "2026-06-01T01:56:14.550448Z",
  "source": "https://aq.nbro.gov.lk/invoker.php",
  "stations": [
    {
      "co2": 469.893,
      "description": "Anuradhapura",
      "latitude": 8.33356,
      "longitude": 80.41497,
      "meta_device_id": "NEAANU00000001",
      "name": "Anuradhapura",
      "now_cast": 15.1965,
      "now_cast_timestamp": 1780273800000,
      "pm10": 7.53333,
      "pm100": 17.25,
      "pm25": 11.671,
      "pm25_band_range": [
        0.0,
        25.0
      ],
      "sl_aqi": 23.0,
      "sl_aqi_est": 23,
      "sl_aqi_label": "Good",
      "sl_aqi_range": [
        0,
        50
      ],
      "temperature": 31.1165,
      "timestamp": 1780273800000,
      "timestamp_iso_utc": "2026-06-01T00:30:00Z",
      "us_aqi": 57.0
    },
    {
      "co2": 511.275,
      "description": "Badulla",
      "latitude": 6.990113,
      "longitude": 81.05676,
      "meta_device_id": "aq02",
      "name": "Badulla ",
      "now_cast": 18.1839,
      "now_cast_timestamp": 1780273800000,
      "pm10": 12.0667,
      "pm100": 19.8,
      "pm25": 17.5262,
      "pm25_band_range": [
        0.0,
        25.0
      ],
      "sl_aqi": 35.0,
      "sl_aqi_est": 35,
      "sl_aqi_label": "Good",
      "sl_aqi_range": [
        0,
        50
      ],
      "temperature": 25.404,
      "timestamp": 1780273800000,
      "timestamp_iso_utc": "2026-06-01T00:30:00Z",
      "us_aqi": 64.0
    },
    {
      "co2": 468.772,
      "description": "aqbatticaloa001",
      "latitude": 7.7124324,
      "longitude": 81.7014,
      "meta_device_id": "BATTI000001",
      "name": "Batticaloa",
      "now_cast": 5.40852,
      "now_cast_timestamp": 1780273800000,
      "pm10": 2.4,
      "pm100": 6.41667,
      "pm25": 5.11421,
      "pm25_band_range": [
        0.0,
        25.0
      ],
      "sl_aqi": 10.0,
      "sl_aqi_est": 10,
      "sl_aqi_label": "Good",
      "sl_aqi_range": [
        0,
        50
      ],
      "temperature": 30.306,
      "timestamp": 1780273800000,
      "timestamp_iso_utc": "2026-06-01T00:30:00Z",
      "us_aqi": 22.0
    },
    {
      "co2": -1.0,
      "description": "Dambulla air quality sensor",
      "latitude": 7.862204,
      "longitude": 80.64585,
      "meta_device_id": "Dav00002",
      "name": "Dambulla",
      "now_cast": 6.02907,
      "now_cast_timestamp": 1780273800000,
      "pm10": 4.58333,
      "pm100": 6.3,
      "pm25": 5.68864,
      "pm25_band_range": [
        0.0,
        25.0
      ],
      "sl_aqi": 11.0,
      "sl_aqi_est": 11,
      "sl_aqi_label": "Good",
      "sl_aqi_range": [
        0,
        50
      ],
      "temperature": 31.2032,
      "timestamp": 1780273800000,
      "timestamp_iso_utc": "2026-06-01T00:30:00Z",
      "us_aqi": 25.0
    },
    {
      "co2": 490.378,
      "description": "Hambantota",
      "latitude": 6.1242557,
      "longitude": 81.12618,
      "meta_device_id": "verit03",
      "name": "Hambantota ",
      "now_cast": 7.79742,
      "now_cast_timestamp": 1780273800000,
      "pm10": 4.15,
      "pm100": 10.1167,
      "pm25": 7.35486,
      "pm25_band_range": [
        0.0,
        25.0
      ],
      "sl_aqi": 14.0,
      "sl_aqi_est": 15,
      "sl_aqi_label": "Good",
      "sl_aqi_range": [
        0,
        50
      ],
      "temperature": 29.991,
      "timestamp": 1780273800000,
      "timestamp_iso_utc": "2026-06-01T00:30:00Z",
      "us_aqi": 32.0
    },
    {
      "co2": 467.059,
      "description": "Jaffna",
      "latitude": 9.737238,
      "longitude": 80.019455,
      "meta_device_id": "JAFPRIVAT0001",
      "name": "Jaffna",
      "now_cast": 6.37151,
      "now_cast_timestamp": 1780273800000,
      "pm10": 2.33333,
      "pm100": 6.51667,
      "pm25": 6.44137,
      "pm25_band_range": [
        0.0,
        25.0
      ],
      "sl_aqi": 13.0,
      "sl_aqi_est": 13,
      "sl_aqi_label": "Good",
      "sl_aqi_range": [
        0,
        50
      ],
      "temperature": 31.1472,
      "timestamp": 1780273800000,
      "timestamp_iso_utc": "2026-06-01T00:30:00Z",
      "us_aqi": 26.0
    },
    {
      "co2": 464.547,
      "description": "Kohuwla",
      "latitude": 6.870283,
      "longitude": 79.8771,
      "meta_device_id": "kohu01",
      "name": "Kohuwla ",
      "now_cast": 2.24069,
      "now_cast_timestamp": 1780273800000,
      "pm10": 1.10169,
      "pm100": 1.94915,
      "pm25": 1.5755,
      "pm25_band_range": [
        0.0,
        25.0
      ],
      "sl_aqi": 3.0,
      "sl_aqi_est": 3,
      "sl_aqi_label": "Good",
      "sl_aqi_range": [
        0,
        50
      ],
      "temperature": 30.671,
      "timestamp": 1780273800000,
      "timestamp_iso_utc": "2026-06-01T00:30:00Z",
      "us_aqi": 9.0
    },
    {
      "co2": -1.0,
      "description": "Kurunegala 1",
      "latitude": 6.835715,
      "longitude": 81.31581,
      "meta_device_id": "NEA8000010",
      "name": "Monaragala",
      "now_cast": 7.36413,
      "now_cast_timestamp": 1780273800000,
      "pm10": 7.38333,
      "pm100": 10.3667,
      "pm25": 9.06415,
      "pm25_band_range": [
        0.0,
        25.0
      ],
      "sl_aqi": 18.0,
      "sl_aqi_est": 18,
      "sl_aqi_label": "Good",
      "sl_aqi_range": [
        0,
        50
      ],
      "temperature": 25.5037,
      "timestamp": 1780273800000,
      "timestamp_iso_utc": "2026-06-01T00:30:00Z",
      "us_aqi": 30.0
    },
    {
      "co2": 472.267,
      "description": "Nuwaraeliya",
      "latitude": 6.9681544,
      "longitude": 80.77159,
      "meta_device_id": "Nuwaraeliya0010",
      "name": "Nuwaraeliya",
      "now_cast": 11.1403,
      "now_cast_timestamp": 1780273800000,
      "pm10": 8.56667,
      "pm100": 12.4833,
      "pm25": 11.163,
      "pm25_band_range": [
        0.0,
        25.0
      ],
      "sl_aqi": 22.0,
      "sl_aqi_est": 22,
      "sl_aqi_label": "Good",
      "sl_aqi_range": [
        0,
        50
      ],
      "temperature": 23.1948,
      "timestamp": 1780273800000,
      "timestamp_iso_utc": "2026-06-01T00:30:00Z",
      "us_aqi": 46.0
    },
    {
      "co2": 497.594,
      "description": "aqpolonnaruwa001",
      "latitude": 7.9132895,
      "longitude": 81.04993,
      "meta_device_id": "polonnaruwa0001",
      "name": "Polonnaruwa",
      "now_cast": 4.91733,
      "now_cast_timestamp": 1780273800000,
      "pm10": 2.75,
      "pm100": 6.3,
      "pm25": 5.46169,
      "pm25_band_range": [
        0.0,
        25.0
      ],
      "sl_aqi": 11.0,
      "sl_aqi_est": 11,
      "sl_aqi_label": "Good",
      "sl_aqi_range": [
        0,
        50
      ],
      "temperature": 29.4177,
      "timestamp": 1780273800000,
      "timestamp_iso_utc": "2026-06-01T00:30:00Z",
      "us_aqi": 20.0
    },
    {
      "co2": -1.0,
      "description": "Rathanapura",
      "latitude": 6.7137103,
      "longitude": 80.38062,
      "meta_device_id": "NEA8000013",
      "name": "Rathnapura ",
      "now_cast": 2.56239,
      "now_cast_timestamp": 1780273800000,
      "pm10": 0.116667,
      "pm100": 2.25,
      "pm25": 1.26643,
      "pm25_band_range": [
        0.0,
        25.0
      ],
      "sl_aqi": 2.0,
      "sl_aqi_est": 3,
      "sl_aqi_label": "Good",
      "sl_aqi_range": [
        0,
        50
      ],
      "temperature": 29.6065,
      "timestamp": 1780273800000,
      "timestamp_iso_utc": "2026-06-01T00:30:00Z",
      "us_aqi": 10.0
    },
    {
      "co2": -1.0,
      "description": "METTRINCOMALEE",
      "latitude": 8.639678,
      "longitude": 81.2028,
      "meta_device_id": "NBROTRINCOMALEE",
      "name": "Trincomalee",
      "now_cast": 8.42641,
      "now_cast_timestamp": 1780273800000,
      "pm10": 5.31667,
      "pm100": 7.66667,
      "pm25": 7.19057,
      "pm25_band_range": [
        0.0,
        25.0
      ],
      "sl_aqi": 14.0,
      "sl_aqi_est": 14,
      "sl_aqi_label": "Good",
      "sl_aqi_range": [
        0,
        50
      ],
      "temperature": 27.3355,
      "timestamp": 1780273800000,
      "timestamp_iso_utc": "2026-06-01T00:30:00Z",
      "us_aqi": 35.0
    },
    {
      "co2": -1.0,
      "description": "Vavuniya",
      "latitude": 8.761628,
      "longitude": 80.49619,
      "meta_device_id": "VAVUNIYA0021",
      "name": "Vavuniya",
      "now_cast": 3.58066,
      "now_cast_timestamp": 1780255800000,
      "pm10": 1.31667,
      "pm100": 3.31667,
      "pm25": 2.13008,
      "pm25_band_range": [
        0.0,
        25.0
      ],
      "sl_aqi": 4.0,
      "sl_aqi_est": 4,
      "sl_aqi_label": "Good",
      "sl_aqi_range": [
        0,
        50
      ],
      "temperature": 35.4282,
      "timestamp": 1780255800000,
      "timestamp_iso_utc": "2026-05-31T19:30:00Z",
      "us_aqi": 14.0
    }
  ]
}
