{
  "count": 15,
  "fetched_at_utc": "2026-05-14T21:37:14.444891Z",
  "source": "https://aq.nbro.gov.lk/invoker.php",
  "stations": [
    {
      "co2": 449.845,
      "description": "Anuradhapura",
      "latitude": 8.33356,
      "longitude": 80.41497,
      "meta_device_id": "NEAANU00000001",
      "name": "Anuradhapura",
      "now_cast": 6.64632,
      "now_cast_timestamp": 1778733000000,
      "pm10": 2.5,
      "pm100": 5.0,
      "pm25": 3.90936,
      "pm25_band_range": [
        0.0,
        25.0
      ],
      "sl_aqi": 8.0,
      "sl_aqi_est": 8,
      "sl_aqi_label": "Good",
      "sl_aqi_range": [
        0,
        50
      ],
      "temperature": 33.67,
      "timestamp": 1778733000000,
      "timestamp_iso_utc": "2026-05-14T04:30:00Z",
      "us_aqi": 27.0
    },
    {
      "co2": 498.129,
      "description": "Badulla",
      "latitude": 6.990113,
      "longitude": 81.05676,
      "meta_device_id": "aq02",
      "name": "Badulla ",
      "now_cast": 50.693,
      "now_cast_timestamp": 1778787000000,
      "pm10": 32.0833,
      "pm100": 53.6167,
      "pm25": 43.5027,
      "pm25_band_range": [
        25.1,
        50.0
      ],
      "sl_aqi": 87.0,
      "sl_aqi_est": 87,
      "sl_aqi_label": "Moderate",
      "sl_aqi_range": [
        51,
        100
      ],
      "temperature": 25.2428,
      "timestamp": 1778787000000,
      "timestamp_iso_utc": "2026-05-14T19:30:00Z",
      "us_aqi": 138.0
    },
    {
      "co2": 409.837,
      "description": "aqbatticaloa001",
      "latitude": 7.7124324,
      "longitude": 81.7014,
      "meta_device_id": "BATTI000001",
      "name": "Batticaloa",
      "now_cast": 18.1442,
      "now_cast_timestamp": 1778787000000,
      "pm10": 10.5667,
      "pm100": 22.45,
      "pm25": 20.0857,
      "pm25_band_range": [
        0.0,
        25.0
      ],
      "sl_aqi": 40.0,
      "sl_aqi_est": 40,
      "sl_aqi_label": "Good",
      "sl_aqi_range": [
        0,
        50
      ],
      "temperature": 28.3972,
      "timestamp": 1778787000000,
      "timestamp_iso_utc": "2026-05-14T19:30:00Z",
      "us_aqi": 64.0
    },
    {
      "co2": -1.0,
      "description": "Dambulla air quality sensor",
      "latitude": 7.862204,
      "longitude": 80.64585,
      "meta_device_id": "Dav00002",
      "name": "Dambulla",
      "now_cast": 7.82036,
      "now_cast_timestamp": 1778787000000,
      "pm10": 5.48333,
      "pm100": 7.73333,
      "pm25": 7.13179,
      "pm25_band_range": [
        0.0,
        25.0
      ],
      "sl_aqi": 14.0,
      "sl_aqi_est": 14,
      "sl_aqi_label": "Good",
      "sl_aqi_range": [
        0,
        50
      ],
      "temperature": 29.6317,
      "timestamp": 1778787000000,
      "timestamp_iso_utc": "2026-05-14T19:30:00Z",
      "us_aqi": 32.0
    },
    {
      "co2": 623.25,
      "description": "Hambantota",
      "latitude": 6.1242557,
      "longitude": 81.12618,
      "meta_device_id": "verit03",
      "name": "Hambantota ",
      "now_cast": 28.3301,
      "now_cast_timestamp": 1778787000000,
      "pm10": 16.6,
      "pm100": 30.4833,
      "pm25": 26.9207,
      "pm25_band_range": [
        25.1,
        50.0
      ],
      "sl_aqi": 54.0,
      "sl_aqi_est": 55,
      "sl_aqi_label": "Moderate",
      "sl_aqi_range": [
        51,
        100
      ],
      "temperature": 29.633,
      "timestamp": 1778787000000,
      "timestamp_iso_utc": "2026-05-14T19:30:00Z",
      "us_aqi": 85.0
    },
    {
      "co2": 424.901,
      "description": "Jaffna",
      "latitude": 9.737238,
      "longitude": 80.019455,
      "meta_device_id": "JAFPRIVAT0001",
      "name": "Jaffna",
      "now_cast": 6.35423,
      "now_cast_timestamp": 1778787000000,
      "pm10": 1.9,
      "pm100": 5.63333,
      "pm25": 5.6783,
      "pm25_band_range": [
        0.0,
        25.0
      ],
      "sl_aqi": 11.0,
      "sl_aqi_est": 11,
      "sl_aqi_label": "Good",
      "sl_aqi_range": [
        0,
        50
      ],
      "temperature": 30.9282,
      "timestamp": 1778787000000,
      "timestamp_iso_utc": "2026-05-14T19:30:00Z",
      "us_aqi": 26.0
    },
    {
      "co2": 446.406,
      "description": "Kohuwla",
      "latitude": 6.870283,
      "longitude": 79.8771,
      "meta_device_id": "kohu01",
      "name": "Kohuwla ",
      "now_cast": 21.6814,
      "now_cast_timestamp": 1778787000000,
      "pm10": 17.2333,
      "pm100": 24.9,
      "pm25": 22.4688,
      "pm25_band_range": [
        0.0,
        25.0
      ],
      "sl_aqi": 44.0,
      "sl_aqi_est": 45,
      "sl_aqi_label": "Good",
      "sl_aqi_range": [
        0,
        50
      ],
      "temperature": 29.2783,
      "timestamp": 1778787000000,
      "timestamp_iso_utc": "2026-05-14T19:30:00Z",
      "us_aqi": 71.0
    },
    {
      "co2": 1454.63,
      "description": "Mannar",
      "latitude": 8.988006,
      "longitude": 79.907524,
      "meta_device_id": "MAN10234s",
      "name": "Mannar",
      "now_cast": 11.8572,
      "now_cast_timestamp": 1778787000000,
      "pm10": 9.86667,
      "pm100": 13.65,
      "pm25": 12.5345,
      "pm25_band_range": [
        0.0,
        25.0
      ],
      "sl_aqi": 25.0,
      "sl_aqi_est": 25,
      "sl_aqi_label": "Good",
      "sl_aqi_range": [
        0,
        50
      ],
      "temperature": 31.3,
      "timestamp": 1778787000000,
      "timestamp_iso_utc": "2026-05-14T19:30:00Z",
      "us_aqi": 49.0
    },
    {
      "co2": -1.0,
      "description": "Kurunegala 1",
      "latitude": 6.835715,
      "longitude": 81.31581,
      "meta_device_id": "NEA8000010",
      "name": "Monaragala",
      "now_cast": 18.3954,
      "now_cast_timestamp": 1778787000000,
      "pm10": 15.7333,
      "pm100": 21.5167,
      "pm25": 19.0841,
      "pm25_band_range": [
        0.0,
        25.0
      ],
      "sl_aqi": 38.0,
      "sl_aqi_est": 38,
      "sl_aqi_label": "Good",
      "sl_aqi_range": [
        0,
        50
      ],
      "temperature": 26.4795,
      "timestamp": 1778787000000,
      "timestamp_iso_utc": "2026-05-14T19:30:00Z",
      "us_aqi": 64.0
    },
    {
      "co2": 413.72,
      "description": "Nuwaraeliya",
      "latitude": 6.9681544,
      "longitude": 80.77159,
      "meta_device_id": "Nuwaraeliya0010",
      "name": "Nuwaraeliya",
      "now_cast": 18.5872,
      "now_cast_timestamp": 1778787000000,
      "pm10": 7.86441,
      "pm100": 13.4746,
      "pm25": 11.2099,
      "pm25_band_range": [
        0.0,
        25.0
      ],
      "sl_aqi": 22.0,
      "sl_aqi_est": 22,
      "sl_aqi_label": "Good",
      "sl_aqi_range": [
        0,
        50
      ],
      "temperature": 21.4498,
      "timestamp": 1778787000000,
      "timestamp_iso_utc": "2026-05-14T19:30:00Z",
      "us_aqi": 64.0
    },
    {
      "co2": 507.148,
      "description": "aqpolonnaruwa001",
      "latitude": 7.9132895,
      "longitude": 81.04993,
      "meta_device_id": "polonnaruwa0001",
      "name": "Polonnaruwa",
      "now_cast": 25.5954,
      "now_cast_timestamp": 1778787000000,
      "pm10": 19.55,
      "pm100": 29.9333,
      "pm25": 26.4459,
      "pm25_band_range": [
        25.1,
        50.0
      ],
      "sl_aqi": 53.0,
      "sl_aqi_est": 54,
      "sl_aqi_label": "Moderate",
      "sl_aqi_range": [
        51,
        100
      ],
      "temperature": 26.9413,
      "timestamp": 1778787000000,
      "timestamp_iso_utc": "2026-05-14T19:30:00Z",
      "us_aqi": 79.0
    },
    {
      "co2": 424.593,
      "description": null,
      "latitude": 8.028199,
      "longitude": 79.84147,
      "meta_device_id": "NEA8000006",
      "name": "Puttalam",
      "now_cast": 12.8879,
      "now_cast_timestamp": 1778787000000,
      "pm10": 7.55932,
      "pm100": 14.4407,
      "pm25": 11.7308,
      "pm25_band_range": [
        0.0,
        25.0
      ],
      "sl_aqi": 23.0,
      "sl_aqi_est": 23,
      "sl_aqi_label": "Good",
      "sl_aqi_range": [
        0,
        50
      ],
      "temperature": 27.2195,
      "timestamp": 1778787000000,
      "timestamp_iso_utc": "2026-05-14T19:30:00Z",
      "us_aqi": 52.0
    },
    {
      "co2": -1.0,
      "description": "Rathanapura",
      "latitude": 6.7137103,
      "longitude": 80.38062,
      "meta_device_id": "NEA8000013",
      "name": "Rathnapura ",
      "now_cast": 11.2084,
      "now_cast_timestamp": 1778769000000,
      "pm10": 6.13333,
      "pm100": 11.0,
      "pm25": 9.87086,
      "pm25_band_range": [
        0.0,
        25.0
      ],
      "sl_aqi": 19.0,
      "sl_aqi_est": 20,
      "sl_aqi_label": "Good",
      "sl_aqi_range": [
        0,
        50
      ],
      "temperature": 27.992,
      "timestamp": 1778769000000,
      "timestamp_iso_utc": "2026-05-14T14:30:00Z",
      "us_aqi": 46.0
    },
    {
      "co2": -1.0,
      "description": "METTRINCOMALEE",
      "latitude": 8.639678,
      "longitude": 81.2028,
      "meta_device_id": "NBROTRINCOMALEE",
      "name": "Trincomalee",
      "now_cast": 5.60178,
      "now_cast_timestamp": 1778787000000,
      "pm10": 3.61667,
      "pm100": 5.01667,
      "pm25": 4.78026,
      "pm25_band_range": [
        0.0,
        25.0
      ],
      "sl_aqi": 9.0,
      "sl_aqi_est": 10,
      "sl_aqi_label": "Good",
      "sl_aqi_range": [
        0,
        50
      ],
      "temperature": 24.5108,
      "timestamp": 1778787000000,
      "timestamp_iso_utc": "2026-05-14T19:30:00Z",
      "us_aqi": 23.0
    },
    {
      "co2": -1.0,
      "description": "Vavuniya",
      "latitude": 8.761628,
      "longitude": 80.49619,
      "meta_device_id": "VAVUNIYA0021",
      "name": "Vavuniya",
      "now_cast": 36.9477,
      "now_cast_timestamp": 1778787000000,
      "pm10": 24.5833,
      "pm100": 46.0333,
      "pm25": 35.8711,
      "pm25_band_range": [
        25.1,
        50.0
      ],
      "sl_aqi": 72.0,
      "sl_aqi_est": 72,
      "sl_aqi_label": "Moderate",
      "sl_aqi_range": [
        51,
        100
      ],
      "temperature": 33.1117,
      "timestamp": 1778787000000,
      "timestamp_iso_utc": "2026-05-14T19:30:00Z",
      "us_aqi": 104.0
    }
  ]
}
